claraterm/ClaraKernel.py
claraterm/__init__.py
claraterm/main.py
claraterm-0.3.6.dist-info/LICENSE
claraterm-0.3.6.dist-info/METADATA
claraterm-0.3.6.dist-info/WHEEL
claraterm-0.3.6.dist-info/entry_points.txt
claraterm-0.3.6.dist-info/top_level.txt
claraterm-0.3.6.dist-info/RECORD
